kvxopt/__init__.py
kvxopt/_version.py
kvxopt/amd.cpython-313-x86_64-linux-musl.so
kvxopt/base.cpython-313-x86_64-linux-musl.so
kvxopt/blas.cpython-313-x86_64-linux-musl.so
kvxopt/cholmod.cpython-313-x86_64-linux-musl.so
kvxopt/coneprog.py
kvxopt/cvxprog.py
kvxopt/fftw.cpython-313-x86_64-linux-musl.so
kvxopt/glpk.cpython-313-x86_64-linux-musl.so
kvxopt/gsl.cpython-313-x86_64-linux-musl.so
kvxopt/info.py
kvxopt/klu.cpython-313-x86_64-linux-musl.so
kvxopt/lapack.cpython-313-x86_64-linux-musl.so
kvxopt/misc.py
kvxopt/misc_solvers.cpython-313-x86_64-linux-musl.so
kvxopt/modeling.py
kvxopt/msk.py
kvxopt/osqp.cpython-313-x86_64-linux-musl.so
kvxopt/printing.py
kvxopt/solvers.py
kvxopt/umfpack.cpython-313-x86_64-linux-musl.so
kvxopt.libs/libamd-47443bfe.so.3.3.3
kvxopt.libs/libbtf-8c8b1f6a.so.2.3.2
kvxopt.libs/libcamd-06deb9f2.so.3.3.3
kvxopt.libs/libccolamd-2f0b232c.so.3.3.4
kvxopt.libs/libcholmod-10e318a5.so.5.3.0
kvxopt.libs/libcolamd-5c0e79bc.so.3.3.4
kvxopt.libs/libfftw3-808d0247.so.3.6.10
kvxopt.libs/libgcc_s-2298274a.so.1
kvxopt.libs/libgfortran-784919c5.so.5.0.0
kvxopt.libs/libglpk-d0d6d601.so.40.3.1
kvxopt.libs/libgmp-eefb79ef.so.10.5.0
kvxopt.libs/libgomp-33954e21.so.1.0.0
kvxopt.libs/libgsl-d1342c11.so.27.0.0
kvxopt.libs/libklu-0ec9db0b.so.2.3.4
kvxopt.libs/libopenblasp-r0-60748ecd.3.28.so
kvxopt.libs/libosqp-86a88a50.so
kvxopt.libs/libquadmath-33050579.so.0.0.0
kvxopt.libs/libsuitesparseconfig-52fb7c5e.so.7.8.2
kvxopt.libs/libumfpack-d3001136.so.6.3.4
kvxopt-1.3.2.2.dist-info/METADATA
kvxopt-1.3.2.2.dist-info/WHEEL
kvxopt-1.3.2.2.dist-info/top_level.txt
kvxopt-1.3.2.2.dist-info/RECORD
kvxopt-1.3.2.2.dist-info/licenses/LICENSE
