Metadata-Version: 2.4
Name: kvxopt
Version: 1.3.2.2
Summary: Convex optimization package and Suite Sparse interface
Home-page: 
Author-email: "M. Andersen" <martin.skovgaard.andersen@gmail.com>, "J. Dahl" <dahl.joachim@gmail.com>, "L. Vandenberghe" <vandenbe@ee.ucla.edu>, "U. Sandoval" <sanurielf@gmail.com>
License-Expression: GPL-3.0-or-later
Project-URL: Source, https://github.com/sanurielf/kvxopt
Classifier: Development Status :: 5 - Production/Stable
Classifier: Intended Audience :: Science/Research
Classifier: Operating System :: OS Independent
Classifier: Programming Language :: C
Classifier: Programming Language :: Python
Classifier: Programming Language :: Python :: 3
Classifier: Topic :: Scientific/Engineering
Requires-Python: >=3.5, !=3.0.*, !=3.1.*, !=3.2.*, !=3.3.*, !=3.4.*
License-File: LICENSE
Requires-Dist: numpy>=1.19.0
Dynamic: license-file
Dynamic: requires-python
